{
  "classname": null,
  "name": null,
  "animation": {
    "classname": null,
    "name": "AnimationManager",
    "actionlist": []
  },
  "dataScale": 1,
  "designHeight": 1136,
  "designWidth": 640,
  "textures": [],
  "texturesPng": [],
  "version": "1.5.0.0",
  "widgetTree": {
    "classname": "Panel",
    "name": null,
    "children": [
      {
        "classname": "Label",
        "name": null,
        "children": [],
        "options": {
          "__type": "LabelSurrogate:#EditorCommon.JsonModel.Component.GUI",
          "classname": "Label",
          "name": "VS",
          "ZOrder": 3,
          "actiontag": 330,
          "anchorPointX": 0.5,
          "anchorPointY": 0.5,
          "classType": "CocoStudio.EngineAdapterWrap.CSLabel",
          "colorB": 255,
          "colorG": 255,
          "colorR": 255,
          "customProperty": "",
          "flipX": false,
          "flipY": false,
          "height": 53,
          "ignoreSize": true,
          "layoutParameter": null,
          "opacity": 255,
          "positionPercentX": 0.5,
          "positionPercentY": 0.44542253,
          "positionType": 0,
          "rotation": 0,
          "scaleX": 1,
          "scaleY": 1,
          "sizePercentX": 0.0890625,
          "sizePercentY": 0.04665493,
          "sizeType": 0,
          "tag": 149,
          "touchAble": false,
          "useMergedTexture": false,
          "visible": true,
          "width": 57,
          "x": 320,
          "y": 506,
          "areaHeight": 0,
          "areaWidth": 0,
          "fontFile": null,
          "fontName": "fonts/Helvetica neue.ttf",
          "fontSize": 45,
          "hAlignment": 0,
          "text": "VS",
          "touchScaleEnable": false,
          "vAlignment": 0
        }
      },
      {
        "classname": "ImageView",
        "name": null,
        "children": [
          {
            "classname": "Label",
            "name": null,
            "children": [],
            "options": {
              "__type": "LabelSurrogate:#EditorCommon.JsonModel.Component.GUI",
              "classname": "Label",
              "name": "team1WinPoint",
              "ZOrder": 0,
              "actiontag": 60,
              "anchorPointX": 0.5,
              "anchorPointY": 0.5,
              "classType": "CocoStudio.EngineAdapterWrap.CSLabel",
              "colorB": 80,
              "colorG": 200,
              "colorR": 92,
              "customProperty": "",
              "flipX": false,
              "flipY": false,
              "height": 47,
              "ignoreSize": true,
              "layoutParameter": null,
              "opacity": 200,
              "positionPercentX": 0,
              "positionPercentY": -0.76953125,
              "positionType": 0,
              "rotation": 0,
              "scaleX": 1,
              "scaleY": 1,
              "sizePercentX": 0.734375,
              "sizePercentY": 0.18359375,
              "sizeType": 0,
              "tag": 11,
              "touchAble": false,
              "useMergedTexture": false,
              "visible": true,
              "width": 188,
              "x": 0,
              "y": -197,
              "areaHeight": 0,
              "areaWidth": 0,
              "fontFile": null,
              "fontName": "fonts/Helvetica neue.ttf",
              "fontSize": 40,
              "hAlignment": 0,
              "text": "%d Points",
              "touchScaleEnable": false,
              "vAlignment": 0
            }
          },
          {
            "classname": "Label",
            "name": null,
            "children": [],
            "options": {
              "__type": "LabelSurrogate:#EditorCommon.JsonModel.Component.GUI",
              "classname": "Label",
              "name": "label001",
              "ZOrder": 0,
              "actiontag": 4537413,
              "anchorPointX": 0.5,
              "anchorPointY": 0.5,
              "classType": "CocoStudio.EngineAdapterWrap.CSLabel",
              "colorB": 255,
              "colorG": 255,
              "colorR": 255,
              "customProperty": "",
              "flipX": false,
              "flipY": false,
              "height": 35,
              "ignoreSize": true,
              "layoutParameter": null,
              "opacity": 200,
              "positionPercentX": 0,
              "positionPercentY": -0.60546875,
              "positionType": 0,
              "rotation": 0,
              "scaleX": 1,
              "scaleY": 1,
              "sizePercentX": 0.67578125,
              "sizePercentY": 0.13671875,
              "sizeType": 0,
              "tag": 8187,
              "touchAble": false,
              "useMergedTexture": false,
              "visible": true,
              "width": 173,
              "x": 0,
              "y": -155,
              "areaHeight": 0,
              "areaWidth": 0,
              "fontFile": null,
              "fontName": "fonts/Helvetica neue.ttf",
              "fontSize": 30,
              "hAlignment": 0,
              "text": "Stand to Win",
              "touchScaleEnable": false,
              "vAlignment": 0
            }
          }
        ],
        "options": {
          "__type": "ImageViewSurrogate:#EditorCommon.JsonModel.Component.GUI",
          "classname": "ImageView",
          "name": "team1",
          "ZOrder": 2,
          "actiontag": 54,
          "anchorPointX": 0.5,
          "anchorPointY": 0.5,
          "classType": "CocoStudio.EngineAdapterWrap.CSImageView",
          "colorB": 255,
          "colorG": 255,
          "colorR": 255,
          "customProperty": "",
          "flipX": false,
          "flipY": false,
          "height": 256,
          "ignoreSize": true,
          "layoutParameter": null,
          "opacity": 255,
          "positionPercentX": 0.240625,
          "positionPercentY": 0.444542259,
          "positionType": 0,
          "rotation": 0,
          "scaleX": 0.8,
          "scaleY": 0.8,
          "sizePercentX": 0.4,
          "sizePercentY": 0.225352108,
          "sizeType": 0,
          "tag": 5,
          "touchAble": true,
          "useMergedTexture": false,
          "visible": true,
          "width": 256,
          "x": 154,
          "y": 505,
          "capInsetsHeight": 0,
          "capInsetsWidth": 0,
          "capInsetsX": 0,
          "capInsetsY": 0,
          "fileName": null,
          "fileNameData": {
            "path": "commonRes/Arsenal.png",
            "plistFile": "",
            "resourceType": 0
          },
          "scale9Enable": false,
          "scale9Height": 256,
          "scale9Width": 256
        }
      },
      {
        "classname": "ImageView",
        "name": null,
        "children": [
          {
            "classname": "Label",
            "name": null,
            "children": [],
            "options": {
              "__type": "LabelSurrogate:#EditorCommon.JsonModel.Component.GUI",
              "classname": "Label",
              "name": "team2WinPoint",
              "ZOrder": 0,
              "actiontag": 65,
              "anchorPointX": 0.5,
              "anchorPointY": 0.5,
              "classType": "CocoStudio.EngineAdapterWrap.CSLabel",
              "colorB": 80,
              "colorG": 200,
              "colorR": 92,
              "customProperty": "",
              "flipX": false,
              "flipY": false,
              "height": 47,
              "ignoreSize": true,
              "layoutParameter": null,
              "opacity": 200,
              "positionPercentX": 0,
              "positionPercentY": -0.76953125,
              "positionType": 0,
              "rotation": 0,
              "scaleX": 1,
              "scaleY": 1,
              "sizePercentX": 0.734375,
              "sizePercentY": 0.18359375,
              "sizeType": 0,
              "tag": 16,
              "touchAble": false,
              "useMergedTexture": false,
              "visible": true,
              "width": 188,
              "x": 0,
              "y": -197,
              "areaHeight": 0,
              "areaWidth": 0,
              "fontFile": null,
              "fontName": "fonts/Helvetica neue.ttf",
              "fontSize": 40,
              "hAlignment": 0,
              "text": "%d Points",
              "touchScaleEnable": false,
              "vAlignment": 0
            }
          },
          {
            "classname": "Label",
            "name": null,
            "children": [],
            "options": {
              "__type": "LabelSurrogate:#EditorCommon.JsonModel.Component.GUI",
              "classname": "Label",
              "name": "label001",
              "ZOrder": 0,
              "actiontag": 59043389,
              "anchorPointX": 0.5,
              "anchorPointY": 0.5,
              "classType": "CocoStudio.EngineAdapterWrap.CSLabel",
              "colorB": 255,
              "colorG": 255,
              "colorR": 255,
              "customProperty": "",
              "flipX": false,
              "flipY": false,
              "height": 35,
              "ignoreSize": true,
              "layoutParameter": null,
              "opacity": 200,
              "positionPercentX": 0,
              "positionPercentY": -0.60546875,
              "positionType": 0,
              "rotation": 0,
              "scaleX": 1,
              "scaleY": 1,
              "sizePercentX": 0.67578125,
              "sizePercentY": 0.13671875,
              "sizeType": 0,
              "tag": 8189,
              "touchAble": false,
              "useMergedTexture": false,
              "visible": true,
              "width": 173,
              "x": 0,
              "y": -155,
              "areaHeight": 0,
              "areaWidth": 0,
              "fontFile": null,
              "fontName": "fonts/Helvetica neue.ttf",
              "fontSize": 30,
              "hAlignment": 0,
              "text": "Stand to Win",
              "touchScaleEnable": false,
              "vAlignment": 0
            }
          }
        ],
        "options": {
          "__type": "ImageViewSurrogate:#EditorCommon.JsonModel.Component.GUI",
          "classname": "ImageView",
          "name": "team2",
          "ZOrder": 2,
          "actiontag": 55,
          "anchorPointX": 0.5,
          "anchorPointY": 0.5,
          "classType": "CocoStudio.EngineAdapterWrap.CSImageView",
          "colorB": 255,
          "colorG": 255,
          "colorR": 255,
          "customProperty": "",
          "flipX": false,
          "flipY": false,
          "height": 256,
          "ignoreSize": true,
          "layoutParameter": null,
          "opacity": 255,
          "positionPercentX": 0.759375,
          "positionPercentY": 0.444542259,
          "positionType": 0,
          "rotation": 0,
          "scaleX": 0.8,
          "scaleY": 0.8,
          "sizePercentX": 0.4,
          "sizePercentY": 0.225352108,
          "sizeType": 0,
          "tag": 6,
          "touchAble": true,
          "useMergedTexture": false,
          "visible": true,
          "width": 256,
          "x": 486,
          "y": 505,
          "capInsetsHeight": 0,
          "capInsetsWidth": 0,
          "capInsetsX": 0,
          "capInsetsY": 0,
          "fileName": null,
          "fileNameData": {
            "path": "commonRes/Manchester United.png",
            "plistFile": "",
            "resourceType": 0
          },
          "scale9Enable": false,
          "scale9Height": 256,
          "scale9Width": 256
        }
      },
      {
        "classname": "Label",
        "name": null,
        "children": [],
        "options": {
          "__type": "LabelSurrogate:#EditorCommon.JsonModel.Component.GUI",
          "classname": "Label",
          "name": "question",
          "ZOrder": 2,
          "actiontag": 62,
          "anchorPointX": 0.5,
          "anchorPointY": 0.5,
          "classType": "CocoStudio.EngineAdapterWrap.CSLabel",
          "colorB": 255,
          "colorG": 255,
          "colorR": 255,
          "customProperty": "",
          "flipX": false,
          "flipY": false,
          "height": 59,
          "ignoreSize": true,
          "layoutParameter": null,
          "opacity": 255,
          "positionPercentX": 0.5,
          "positionPercentY": 0.7403169,
          "positionType": 0,
          "rotation": 0,
          "scaleX": 1,
          "scaleY": 1,
          "sizePercentX": 0.7359375,
          "sizePercentY": 0.05193662,
          "sizeType": 0,
          "tag": 13,
          "touchAble": false,
          "useMergedTexture": false,
          "visible": true,
          "width": 471,
          "x": 320,
          "y": 841,
          "areaHeight": 0,
          "areaWidth": 0,
          "fontFile": null,
          "fontName": "fonts/Helvetica neue.ttf",
          "fontSize": 50,
          "hAlignment": 1,
          "text": "Which team will win?",
          "touchScaleEnable": false,
          "vAlignment": 1
        }
      },
      {
        "classname": "Label",
        "name": null,
        "children": [],
        "options": {
          "__type": "LabelSurrogate:#EditorCommon.JsonModel.Component.GUI",
          "classname": "Label",
          "name": "stake",
          "ZOrder": 0,
          "actiontag": 19,
          "anchorPointX": 0,
          "anchorPointY": 0.5,
          "classType": "CocoStudio.EngineAdapterWrap.CSLabel",
          "colorB": 59,
          "colorG": 54,
          "colorR": 254,
          "customProperty": "",
          "flipX": false,
          "flipY": false,
          "height": 29,
          "ignoreSize": true,
          "layoutParameter": null,
          "opacity": 255,
          "positionPercentX": 0.4546875,
          "positionPercentY": 0.6047535,
          "positionType": 0,
          "rotation": 0,
          "scaleX": 1,
          "scaleY": 1,
          "sizePercentX": 0.1828125,
          "sizePercentY": 0.0255281683,
          "sizeType": 0,
          "tag": 926,
          "touchAble": false,
          "useMergedTexture": false,
          "visible": true,
          "width": 117,
          "x": 291,
          "y": 687,
          "areaHeight": 0,
          "areaWidth": 0,
          "fontFile": null,
          "fontName": "fonts/Helvetica neue.ttf",
          "fontSize": 25,
          "hAlignment": 0,
          "text": "%d Points",
          "touchScaleEnable": false,
          "vAlignment": 0
        }
      },
      {
        "classname": "Label",
        "name": null,
        "children": [],
        "options": {
          "__type": "LabelSurrogate:#EditorCommon.JsonModel.Component.GUI",
          "classname": "Label",
          "name": "balance",
          "ZOrder": 0,
          "actiontag": 20,
          "anchorPointX": 0,
          "anchorPointY": 0.5,
          "classType": "CocoStudio.EngineAdapterWrap.CSLabel",
          "colorB": 80,
          "colorG": 200,
          "colorR": 92,
          "customProperty": "",
          "flipX": false,
          "flipY": false,
          "height": 35,
          "ignoreSize": true,
          "layoutParameter": null,
          "opacity": 255,
          "positionPercentX": 0.4546875,
          "positionPercentY": 0.6382042,
          "positionType": 0,
          "rotation": 0,
          "scaleX": 1,
          "scaleY": 1,
          "sizePercentX": 0.21875,
          "sizePercentY": 0.0308098588,
          "sizeType": 0,
          "tag": 927,
          "touchAble": false,
          "useMergedTexture": false,
          "visible": true,
          "width": 140,
          "x": 291,
          "y": 725,
          "areaHeight": 0,
          "areaWidth": 0,
          "fontFile": null,
          "fontName": "fonts/Helvetica neue.ttf",
          "fontSize": 30,
          "hAlignment": 0,
          "text": "%d Points",
          "touchScaleEnable": false,
          "vAlignment": 0
        }
      },
      {
        "classname": "Label",
        "name": null,
        "children": [],
        "options": {
          "__type": "LabelSurrogate:#EditorCommon.JsonModel.Component.GUI",
          "classname": "Label",
          "name": "label001",
          "ZOrder": 0,
          "actiontag": 50891251,
          "anchorPointX": 1,
          "anchorPointY": 0.5,
          "classType": "CocoStudio.EngineAdapterWrap.CSLabel",
          "colorB": 255,
          "colorG": 255,
          "colorR": 255,
          "customProperty": "",
          "flipX": false,
          "flipY": false,
          "height": 29,
          "ignoreSize": true,
          "layoutParameter": null,
          "opacity": 255,
          "positionPercentX": 0.4421875,
          "positionPercentY": 0.6382042,
          "positionType": 0,
          "rotation": 0,
          "scaleX": 1,
          "scaleY": 1,
          "sizePercentX": 0.1390625,
          "sizePercentY": 0.0255281683,
          "sizeType": 0,
          "tag": 8191,
          "touchAble": false,
          "useMergedTexture": false,
          "visible": true,
          "width": 89,
          "x": 283,
          "y": 725,
          "areaHeight": 0,
          "areaWidth": 0,
          "fontFile": null,
          "fontName": "fonts/Helvetica neue.ttf",
          "fontSize": 25,
          "hAlignment": 0,
          "text": "Balance",
          "touchScaleEnable": false,
          "vAlignment": 0
        }
      },
      {
        "classname": "Label",
        "name": null,
        "children": [],
        "options": {
          "__type": "LabelSurrogate:#EditorCommon.JsonModel.Component.GUI",
          "classname": "Label",
          "name": "label002",
          "ZOrder": 0,
          "actiontag": 51789483,
          "anchorPointX": 1,
          "anchorPointY": 0.5,
          "classType": "CocoStudio.EngineAdapterWrap.CSLabel",
          "colorB": 255,
          "colorG": 255,
          "colorR": 255,
          "customProperty": "",
          "flipX": false,
          "flipY": false,
          "height": 29,
          "ignoreSize": true,
          "layoutParameter": null,
          "opacity": 255,
          "positionPercentX": 0.4421875,
          "positionPercentY": 0.6056338,
          "positionType": 0,
          "rotation": 0,
          "scaleX": 1,
          "scaleY": 1,
          "sizePercentX": 0.0984375,
          "sizePercentY": 0.0255281683,
          "sizeType": 0,
          "tag": 8193,
          "touchAble": false,
          "useMergedTexture": false,
          "visible": true,
          "width": 63,
          "x": 283,
          "y": 688,
          "areaHeight": 0,
          "areaWidth": 0,
          "fontFile": null,
          "fontName": "fonts/Helvetica neue.ttf",
          "fontSize": 25,
          "hAlignment": 0,
          "text": "Stake",
          "touchScaleEnable": false,
          "vAlignment": 0
        }
      }
    ],
    "options": {
      "__type": "PanelSurrogate:#EditorCommon.JsonModel.Component.GUI",
      "classname": "Panel",
      "name": "Panel_50",
      "ZOrder": 0,
      "actiontag": -1,
      "anchorPointX": 0,
      "anchorPointY": 0,
      "classType": "CocoStudio.EngineAdapterWrap.CSPanel",
      "colorB": 255,
      "colorG": 255,
      "colorR": 255,
      "customProperty": "",
      "flipX": false,
      "flipY": false,
      "height": 1136,
      "ignoreSize": false,
      "layoutParameter": null,
      "opacity": 255,
      "positionPercentX": 0,
      "positionPercentY": 0,
      "positionType": 0,
      "rotation": 0,
      "scaleX": 1,
      "scaleY": 1,
      "sizePercentX": 1,
      "sizePercentY": 1,
      "sizeType": 0,
      "tag": 2,
      "touchAble": false,
      "useMergedTexture": false,
      "visible": true,
      "width": 640,
      "x": 0,
      "y": 0,
      "adaptScreen": false,
      "backGroundImage": null,
      "backGroundImageData": null,
      "backGroundScale9Enable": false,
      "bgColorB": 255,
      "bgColorG": 200,
      "bgColorOpacity": 0,
      "bgColorR": 150,
      "bgEndColorB": 255,
      "bgEndColorG": 200,
      "bgEndColorR": 150,
      "bgStartColorB": 255,
      "bgStartColorG": 255,
      "bgStartColorR": 255,
      "capInsetsHeight": 0,
      "capInsetsWidth": 0,
      "capInsetsX": 0,
      "capInsetsY": 0,
      "clipAble": false,
      "colorType": 0,
      "layoutType": 0,
      "vectorX": 0,
      "vectorY": -0.5
    }
  }
}